users/__init__.py
users/admin.py
users/apps.py
users/forms.py
users/models.py
users/migrations/0001_initial.py
users/migrations/0002_alter_user_id.py
users/migrations/__init__.py
django_email_users-2.1.0.dist-info/METADATA
django_email_users-2.1.0.dist-info/WHEEL
django_email_users-2.1.0.dist-info/licenses/AUTHORS.rst
django_email_users-2.1.0.dist-info/licenses/LICENSE
django_email_users-2.1.0.dist-info/RECORD
