Metadata-Version: 2.4
Name: django-email-users
Version: 2.1.0
Summary: Stock user app but without usernames
Project-URL: Homepage, https://github.com/bennylope/django-email-users
Author-email: Ben Lopatin <ben@benlopatin.com>
License: BSD License
License-File: AUTHORS.rst
License-File: LICENSE
Keywords: django-email-users
Classifier: Development Status :: 4 - Beta
Classifier: Framework :: Django
Classifier: Intended Audience :: Developers
Classifier: License :: OSI Approved :: BSD License
Classifier: Natural Language :: English
Classifier: Programming Language :: Python :: 3
Classifier: Programming Language :: Python :: 3.9
Classifier: Programming Language :: Python :: 3.10
Classifier: Programming Language :: Python :: 3.11
Classifier: Programming Language :: Python :: 3.12
Classifier: Programming Language :: Python :: 3.13
Requires-Python: >=3.8
Provides-Extra: linting
Requires-Dist: flake8; extra == 'linting'
Requires-Dist: isort; extra == 'linting'
Provides-Extra: tests
Requires-Dist: coverage; extra == 'tests'
Requires-Dist: pytest-cov>=2.4.0; extra == 'tests'
Requires-Dist: pytest-django>=3.0.0; extra == 'tests'
Requires-Dist: pytest>=6.0; extra == 'tests'
